echelon_client/__init__.py
echelon_client/crendentials.db
echelon_client/echelon.py
echelon_client/echelon_window.py
echelon_client/echelon_wizard.py
echelon_client/classes/__init__.py
echelon_client/classes/echelon_agent.py
echelon_client/classes/echelon_client_factory.py
echelon_client/classes/echelon_console.py
echelon_client/classes/echelon_encoder.py
echelon_client/conf/__init__.py
echelon_client/conf/config.ini
echelon_client/logs/__init__.py
echelon_client/logs/echelon_command.log
echelon_client/utils/__init__.py
echelon_client/utils/config_loader.py
echelon_client/utils/constants.py
echelon_client/utils/db.py
echelon_client/utils/utils.py
echelon_client_agent-0.0.5.dist-info/METADATA
echelon_client_agent-0.0.5.dist-info/RECORD
echelon_client_agent-0.0.5.dist-info/WHEEL
echelon_client_agent-0.0.5.dist-info/top_level.txt
