Metadata-Version: 2.1
Name: echelon-client-agent
Version: 0.0.5
Summary: Communication Agent
Home-page: https://bitbucket.org/connecttix/echelon-client
Author: Inka-labs
Author-email: eduardo@inka-labs.com
License: UNKNOWN
Platform: UNKNOWN
Classifier: Programming Language :: Python :: 3
Classifier: License :: OSI Approved :: MIT License
Classifier: Operating System :: OS Independent
Requires-Dist: attrs (==17.4.0)
Requires-Dist: Automat (==0.6.0)
Requires-Dist: certifi (==2018.4.16)
Requires-Dist: chardet (==3.0.4)
Requires-Dist: constantly (==15.1.0)
Requires-Dist: dicttoxml (==1.7.4)
Requires-Dist: hyperlink (==18.0.0)
Requires-Dist: idna (==2.6)
Requires-Dist: incremental (==17.5.0)
Requires-Dist: pytz (==2017.3)
Requires-Dist: requests (==2.18.4)
Requires-Dist: six (==1.11.0)
Requires-Dist: SQLAlchemy (==1.2.1)
Requires-Dist: Twisted (==18.4.0)
Requires-Dist: urllib3 (==1.22)
Requires-Dist: zope.interface (==4.5.0)
